boncord-0.0.0.dist-info/METADATA
boncord-0.0.0.dist-info/WHEEL
boncord/__init__.py
boncord-0.0.0.dist-info/RECORD
